LICENSE
MANIFEST.in
README.md
enable_ipypivot.json
requirements.txt
setup.cfg
setup.py
ipypivot/__init__.py
ipypivot/__meta__.py
ipypivot/_config.py
ipypivot/_options.py
ipypivot/_sample.py
ipypivot/_state.py
ipypivot/_widget_pivot.py
ipypivot/_widget_pivotui.py
ipypivot/_widget_pivotui_box.py
ipypivot/_widget_util.py
ipypivot/_wrapper.py
ipypivot.egg-info/PKG-INFO
ipypivot.egg-info/SOURCES.txt
ipypivot.egg-info/dependency_links.txt
ipypivot.egg-info/not-zip-safe
ipypivot.egg-info/requires.txt
ipypivot.egg-info/top_level.txt
ipypivot/api/pivot.json
ipypivot/api/pivotui.json
ipypivot/data/iris.csv
ipypivot/data/mps.csv
ipypivot/data/tips.csv
ipypivot/data/weather.csv
ipypivot/markdown/pivotui.md
ipypivot/static/extension.js
ipypivot/static/index.js
ipypivot/static/index.js.map