Metadata-Version: 1.1
Name: ipypivot
Version: 0.2.6
Summary: Jupyter widget (or ipywidget) wrapping the very convenient pivotTable.js library
Home-page: https://github.com/PierreMarion23/ipypivot
Author: PierreMarion23
Author-email: pierre23.marion@free.fr
License: MIT
Download-URL: https://github.com/PierreMarion23/ipypivot/tarball/0.2.6
Keywords: jupyter-widget,javascript,pivottable
Platform: UNKNOWN
Classifier: Development Status :: 4 - Beta
Classifier: License :: OSI Approved :: MIT License
Classifier: Programming Language :: Python :: 3.5
Classifier: Programming Language :: Python :: 3.6
